package_InstaDown/Cookie_creator.py
package_InstaDown/InstaDown.py
package_InstaDown/__init__.py
InstaDown_new-2.0b0.dist-info/LICENSE
InstaDown_new-2.0b0.dist-info/METADATA
InstaDown_new-2.0b0.dist-info/WHEEL
InstaDown_new-2.0b0.dist-info/top_level.txt
InstaDown_new-2.0b0.dist-info/RECORD
