Metadata-Version: 2.1
Name: InstaDown-new
Version: 2.0b0
Summary: Script to download pictures from a list of Instagram post URLs
Author-email: Giovanni Daniele Starita <gstarita94@gmail.com>
License: MIT License        
Project-URL: Homepage, https://github.com/giovsta/InstaDown
Project-URL: Bug Tracker, https://github.com/giovsta/InstaDown/issues
Classifier: Programming Language :: Python :: 3
Classifier: License :: OSI Approved :: MIT License
Classifier: Operating System :: OS Independent
Requires-Python: >=3.7
License-File: LICENSE
